mistune_slack/__init__.py
mistune_slack/plugin.py
mistune_slack/py.typed
mistune_slack/renderer.py
mistune_slack/util.py
mistune_slack-0.1.4.dist-info/METADATA
mistune_slack-0.1.4.dist-info/WHEEL
mistune_slack-0.1.4.dist-info/entry_points.txt
mistune_slack-0.1.4.dist-info/licenses/LICENSE
mistune_slack-0.1.4.dist-info/RECORD
