Metadata-Version: 2.4
Name: mistune-slack
Version: 0.1.4
Summary: Convert Markdown to Slack blocks - useful for chatbots
Project-URL: Homepage, https://github.com/Submersible/python-mistune-slack
Project-URL: Repository, https://github.com/Submersible/python-mistune-slack
Project-URL: Documentation, https://github.com/Submersible/python-mistune-slack#readme
Project-URL: Bug Tracker, https://github.com/Submersible/python-mistune-slack/issues
Author-email: Ryan Munro <500774+munro@users.noreply.github.com>
License: MIT
License-File: LICENSE
Keywords: block-kit,markdown,mistune,renderer,slack
Classifier: Development Status :: 5 - Production/Stable
Classifier: Intended Audience :: Developers
Classifier: License :: OSI Approved :: MIT License
Classifier: Programming Language :: Python :: 3
Classifier: Programming Language :: Python :: 3.11
Classifier: Programming Language :: Python :: 3.12
Classifier: Programming Language :: Python :: 3.13
Classifier: Topic :: Software Development :: Libraries
Classifier: Topic :: Text Processing :: Markup
Requires-Python: <4,>=3.11
Requires-Dist: mistune<4,>=3
Requires-Dist: typing-extensions>=4.13.2
